pytc2/__init__.py
pytc2/cuadripolos.py
pytc2/dibujar.py
pytc2/filtros_digitales.py
pytc2/general.py
pytc2/ltspice.py
pytc2/ltspice_equalizador_base.asc
pytc2/ltspice_equalizador_base.plt
pytc2/remociones.py
pytc2/sintesis_dipolo.py
pytc2/sistemas_lineales.py
pytc2-0.2.1.dist-info/AUTHORS.md
pytc2-0.2.1.dist-info/LICENSE
pytc2-0.2.1.dist-info/METADATA
pytc2-0.2.1.dist-info/WHEEL
pytc2-0.2.1.dist-info/RECORD
