Metadata-Version: 2.1
Name: pytc2
Version: 0.2.1
Summary: Módulo didáctico para el estudio de Teoría de Circuitos
License: MIT
Author: Mariano Llamedo Soria
Requires-Python: >=3.9,<3.13
Classifier: License :: OSI Approved :: MIT License
Classifier: Programming Language :: Python :: 3
Classifier: Programming Language :: Python :: 3.9
Classifier: Programming Language :: Python :: 3.10
Classifier: Programming Language :: Python :: 3.11
Classifier: Programming Language :: Python :: 3.12
Requires-Dist: jupyter (>=1.0.0)
Requires-Dist: matplotlib (>=3.7.0)
Requires-Dist: numpy (>=1.24.2)
Requires-Dist: schemdraw (>=0.15)
Requires-Dist: scipy (>=1.10.1)
Requires-Dist: sympy (>=1.11.1)
